{
  "menu": [
    {
      "url": "/dashboard",
      "name": "Dashboard",
      "icon": "menu-icon tf-icons bx bx-home-circle",
      "slug": "dashboard"
    },
    {
      "menuHeader": "Usuarios"
    },
    {
      "url": "minitoreo/usuarios",
      "name": " Listado de usuarios",
      "icon": "menu-icon bx bxs-user-detail bx-flip-horizontal bx-tada",
      "slug": "app-email"
    },
    {
      "menuHeader": "Empresas"
    },
    {
      "url": "monitoreo/empresas",
      "name": " Listado de empresas",
      "icon": "menu-icon bx bx-hard-hat",
      "slug": "app-email"
    },
    {
      "menuHeader": "Reportes"
    },
    {
      "name": "Cards",
      "icon": "menu-icon tf-icons bx bx-collection",
      "slug": "cards-basic",
      "url": "cards/basic"
    },

    {
      "url": "https://demos.themeselection.com/sneat-bootstrap-html-laravel-admin-template/demo-1/tables/datatables-basic",
      "icon": "menu-icon tf-icons bx bx-grid",
      "name": "Datatables",
      "slug": "tables-datatables",
      "target": "_blank"
    },
    {
      "menuHeader": "Roles y Permisos"
    },
    {
      "url": "https://github.com/themeselection/sneat-bootstrap-html-laravel-admin-template-free/issues",
      "icon": "menu-icon tf-icons bx bx-support",
      "name": "Roles",
      "slug": "support",
      "target": "_blank"
    }
  ]
}
